slack_github_triager_core/__init__.py
slack_github_triager_core/github.py
slack_github_triager_core/github_client.py
slack_github_triager_core/processing.py
slack_github_triager_core/slack.py
slack_github_triager_core/slack_client.py
slack_github_triager_core-0.3.3.dist-info/METADATA
slack_github_triager_core-0.3.3.dist-info/WHEEL
slack_github_triager_core-0.3.3.dist-info/RECORD
