Metadata-Version: 2.4
Name: slack-github-triager-core
Version: 0.3.3
Summary: Core library for Slack-GitHub triaging functionality
Author-email: Eli Block <3347571+eliblock@users.noreply.github.com>
License: MIT
Requires-Python: >=3.11
Requires-Dist: pyjwt[crypto]>=2.10.1
Requires-Dist: requests>=2.31.0
Provides-Extra: dev
